{"name":"RexQ","google":"UA-35129695-4","tagline":"Job queueing, scheduling, and asynchronous execution","note":"Don't delete this file! It's used internally to help with page regeneration.","body":"### Summary\r\nAn asynchronous job execution engine, inspired by Resque and SideKiq.\r\n\r\n### Trying it out\r\n```\r\n$ eval `perl -Mlocal::lib=/tmp/rexq`\r\n$ cpanm -l /tmp/rexq https://github.com/niczero/rexq.git\r\n```\r\n\r\n### Authors and Contributors\r\nDiego Kuperman wrote http://diegok.github.com/resque-perl, a perl port of http://defunkt.github.com/resque.  Diego appears on irc://irc.perl.org/mojo as ```diegok``` and has taken time to explain some of his design decisions.  His code is on CPAN as Resque (http://metacpan.org/module/Resque) and he has been using it in production since late 2011.\r\n\r\n### Support or Contact\r\nThe best channel for discussing this code is irc://irc.perl.org/mojo where you might catch me as ```nic```."}